{
  "bmts": {
    "4a5b6e82-a048-5c96-8734-2f64d2288378": {
      "enabled": true,
      "runner": {
        "uri": "projects/sk/kardome_runner",
        "deps_prefix": "projects/sk/lib"
      },
      "template_uri": "projects/shared/input_template.json",
      "paths": {
        "dataset_prefix": "projects/sk/inputs/false_rejects",
        "outputs_prefix": "projects/sk/outputs/false_rejects",
        "results_prefix": "projects/sk/results/false_rejects",
        "logs_prefix": "projects/sk/results/logs/false_rejects"
      },
      "runtime": {
        "num_source_test": 0,
        "enable_overrides": {
          "KWS_CONFIG.KWS_ENABLE": true,
          "BIOMETRICS_CONFIG.BIO_ENABLE": false
        },
        "cache": {
          "enabled": true,
          "root": "./cache",
          "dataset_ttl_sec": 300
        }
      },
      "gate": {
        "comparison": "gte",
        "tolerance_abs": 0.25
      },
      "warning_policy": {
        "bootstrap_without_baseline": true
      },
      "demo": {
        "force_pass": false
      },
      "artifacts": {
        "upload_outputs": false,
        "upload_outputs_contexts": ["manual"]
      },
      "parsing": {
        "keyword": "NAMUH",
        "counter_pattern": "Hi NAMUH counter = (\\d+)"
      }
    },
    "ac73397e-1162-5004-9ca2-17c969f53ee5": {
      "enabled": true,
      "runner": {
        "uri": "projects/sk/kardome_runner",
        "deps_prefix": "projects/sk/lib"
      },
      "template_uri": "projects/shared/input_template.json",
      "paths": {
        "dataset_prefix": "projects/sk/inputs/false_alarms",
        "outputs_prefix": "projects/sk/outputs/false_alarms",
        "results_prefix": "projects/sk/results/false_alarms",
        "logs_prefix": "projects/sk/results/logs/false_alarms"
      },
      "runtime": {
        "num_source_test": 0,
        "enable_overrides": {
          "KWS_CONFIG.KWS_ENABLE": true,
          "BIOMETRICS_CONFIG.BIO_ENABLE": false
        },
        "cache": {
          "enabled": true,
          "root": "./cache",
          "dataset_ttl_sec": 300
        }
      },
      "gate": {
        "comparison": "lte",
        "tolerance_abs": 0.25
      },
      "warning_policy": {
        "bootstrap_without_baseline": true
      },
      "demo": {
        "force_pass": false
      },
      "artifacts": {
        "upload_outputs": false,
        "upload_outputs_contexts": ["manual"]
      },
      "parsing": {
        "keyword": "NAMUH",
        "counter_pattern": "Hi NAMUH counter = (\\d+)"
      }
    }
  }
}
