{
  "schema_version": 1,
  "project": "sk",
  "bmt_slug": "false_alarms",
  "bmt_id": "ac73397e-1162-5004-9ca2-17c969f53ee5",
  "enabled": true,
  "plugin_ref": "published:default:sha256-e47e6ea5e6cf12aa057d9d6e7ba9ecc5c69151fefee87334db5ce36f4be1109a",
  "inputs_prefix": "projects/sk/inputs/false_alarms",
  "results_prefix": "projects/sk/results/false_alarms",
  "outputs_prefix": "projects/sk/outputs/false_alarms",
  "runner": {
    "uri": "projects/sk/runner_bundle/kardome_runner",
    "deps_prefix": "projects/shared/dependencies",
    "template_path": "gcp/image/runtime/assets/kardome_input_template.json"
  },
  "execution": {
    "policy": "adaptive_batch_then_legacy"
  },
  "plugin_config": {
    "comparison": "lte",
    "tolerance_abs": 0.25,
    "keyword": "NAMUH",
    "counter_pattern": "Hi NAMUH counter = (\\d+)",
    "num_source_test": 0,
    "enable_overrides": {
      "KWS_CONFIG.KWS_ENABLE": true,
      "BIOMETRICS_CONFIG.BIO_ENABLE": false
    }
  }
}
